hcloud_selfdestruct/__init__.py
hcloud_selfdestruct-0.1.1.dist-info/LICENSE
hcloud_selfdestruct-0.1.1.dist-info/METADATA
hcloud_selfdestruct-0.1.1.dist-info/WHEEL
hcloud_selfdestruct-0.1.1.dist-info/entry_points.txt
hcloud_selfdestruct-0.1.1.dist-info/RECORD
