Metadata-Version: 2.1
Name: hcloud-selfdestruct
Version: 0.1.1
Summary: cli tool to self destruct a hetzner cloud server
Home-page: https://github.com/worldworm/hcloud-selfdestruct
License: MIT
Keywords: selfdestruct,hcloud,hetzner
Author: worldworm
Requires-Python: >=3.8,<4.0
Classifier: License :: OSI Approved :: MIT License
Classifier: Programming Language :: Python :: 3
Classifier: Programming Language :: Python :: 3.8
Classifier: Programming Language :: Python :: 3.9
Classifier: Programming Language :: Python :: 3.10
Classifier: Programming Language :: Python :: 3.11
Classifier: Programming Language :: Python :: 3.12
Requires-Dist: apprise (>=1.2.1,<2.0.0)
Requires-Dist: hcloud (>=1.18.2,<2.0.0)
Project-URL: Repository, https://github.com/worldworm/hcloud-selfdestruct
